{
  "efficienza_mensile": 65.9871798642735,
  "media_giornaliera": 98.5910652920962,
  "media_mensile_pk": 105.544451208002,
  "foglio_report": "Giugno 2026",
  "foglio_colli": "23-06-2026",
  "data_dashboard": "23/06/2026",
  "ultimo_aggiornamento": "23/06/2026 15:20:13",
  "trend_orario": [
    {
      "media": 0,
      "ora": "4"
    },
    {
      "media": 0,
      "ora": "5"
    },
    {
      "media": 105.607142857143,
      "ora": "6"
    },
    {
      "media": 107.52380952381,
      "ora": "7"
    },
    {
      "media": 112.058139534884,
      "ora": "8"
    },
    {
      "media": 76.020618556701,
      "ora": "9"
    },
    {
      "media": 106.072164948454,
      "ora": "10"
    },
    {
      "media": 91.4432989690722,
      "ora": "11"
    },
    {
      "media": 96.1333333333333,
      "ora": "12"
    },
    {
      "media": 92.7294117647059,
      "ora": "13"
    },
    {
      "media": 92.8313253012048,
      "ora": "14"
    },
    {
      "media": 110.828571428571,
      "ora": "15"
    },
    {
      "media": 0,
      "ora": "16"
    },
    {
      "media": 0,
      "ora": "17"
    },
    {
      "media": 0,
      "ora": "18"
    },
    {
      "media": 0,
      "ora": "19"
    },
    {
      "media": 0,
      "ora": "20"
    }
  ]
}
